{
  "$type": "Game.GameMode.StorySession.GameBoard.Simulation.Items.Enteties.Item, Game.GameMode.StorySession",
  "ItemId": "rapier_bronze",
  "ItemSetId": "melee_core",
  "ItemName": "rapier",
  "ItemRarity": 0,
  "ItemSize": 2,
  "UpgradedItemId": "rapier_silver",
  "DowngradedItemId": null,
  "ItemSpriteRuntimeKey": "1ff8cf2e9e5aff74882859ff8922d14e[rapier_0]",
  "Tags": {
    "$type": "Game.GameMode.StorySession.GameBoard.Simulation.Items.Enteties.Special.Tags.TagList, Game.GameMode.StorySession",
    "TagsList": {
      "$type": "System.Collections.Generic.List`1[[Game.GameMode.StorySession.GameBoard.Simulation.Items.Enteties.Special.Tags.ItemTag, Game.GameMode.StorySession]], mscorlib",
      "$values": [
        1,
        3,
        11
      ]
    }
  },
  "Triggers": {
    "$type": "System.Collections.Generic.List`1[[Game.GameMode.StorySession.GameBoard.Simulation.Items.Enteties.Structure.Trigger, Game.GameMode.StorySession]], mscorlib",
    "$values": [
      {
        "$type": "Game.GameMode.StorySession.GameBoard.Simulation.Items.Enteties.Triggers.OnChargedTrigger, Game.GameMode.StorySession",
        "Effectors": {
          "$type": "System.Collections.Generic.List`1[[Game.GameMode.StorySession.GameBoard.Simulation.Items.Enteties.Structure.Effector, Game.GameMode.StorySession]], mscorlib",
          "$values": [
            {
              "$type": "Game.GameMode.StorySession.GameBoard.Simulation.Items.Enteties.Effectors.DealDamageEffector, Game.GameMode.StorySession",
              "TargetSelector": {
                "$type": "Game.GameMode.StorySession.GameBoard.Simulation.Items.Enteties.TargetSelectors.EnemyTargetSelector, Game.GameMode.StorySession"
              },
              "DamageStatProvider": {
                "$type": "Game.GameMode.StorySession.GameBoard.Simulation.Items.Enteties.StatProviders.UniversalItemStatProvider, Game.GameMode.StorySession",
                "Multiplier": 1.0
              },
              "IsCritAvailable": true
            }
          ]
        }
      }
    ]
  },
  "ItemStats": {
    "$type": "Game.GameMode.StorySession.GameBoard.Simulation.Items.Enteties.Special.ItemStatSets.ItemStatSet, Game.GameMode.StorySession",
    "Stats": {
      "$type": "System.Collections.Generic.Dictionary`2[[Game.GameMode.StorySession.GameBoard.Simulation.Items.Enteties.Special.ItemStatSets.ItemStatType, Game.GameMode.StorySession],[Game.GameMode.StorySession.GameBoard.Simulation.Items.Enteties.Special.ItemStatSets.ItemStatEntry, Game.GameMode.StorySession]], mscorlib",
      "Value": {
        "$type": "Game.GameMode.StorySession.GameBoard.Simulation.Items.Enteties.Special.ItemStatSets.ItemStatEntry, Game.GameMode.StorySession",
        "ItemValues": {
          "$type": "Game.GameMode.StorySession.GameBoard.Simulation.Utilities.StatSet, Game.GameMode.StorySession",
          "Stats": {
            "$type": "System.Single[], mscorlib",
            "$values": [
              2.0,
              0.0,
              0.0,
              0.0,
              0.0
            ]
          }
        },
        "ItemPercentiles": {
          "$type": "Game.GameMode.StorySession.GameBoard.Simulation.Utilities.StatSet, Game.GameMode.StorySession",
          "Stats": {
            "$type": "System.Single[], mscorlib",
            "$values": [
              1.0,
              1.0,
              1.0,
              1.0,
              1.0
            ]
          }
        }
      },
      "Damage": {
        "$type": "Game.GameMode.StorySession.GameBoard.Simulation.Items.Enteties.Special.ItemStatSets.ItemStatEntry, Game.GameMode.StorySession",
        "ItemValues": {
          "$type": "Game.GameMode.StorySession.GameBoard.Simulation.Utilities.StatSet, Game.GameMode.StorySession",
          "Stats": {
            "$type": "System.Single[], mscorlib",
            "$values": [
              20.0,
              0.0,
              0.0,
              0.0,
              0.0
            ]
          }
        },
        "ItemPercentiles": {
          "$type": "Game.GameMode.StorySession.GameBoard.Simulation.Utilities.StatSet, Game.GameMode.StorySession",
          "Stats": {
            "$type": "System.Single[], mscorlib",
            "$values": [
              1.0,
              1.0,
              1.0,
              1.0,
              1.0
            ]
          }
        }
      },
      "CriticalChance": {
        "$type": "Game.GameMode.StorySession.GameBoard.Simulation.Items.Enteties.Special.ItemStatSets.ItemStatEntry, Game.GameMode.StorySession",
        "ItemValues": {
          "$type": "Game.GameMode.StorySession.GameBoard.Simulation.Utilities.StatSet, Game.GameMode.StorySession",
          "Stats": {
            "$type": "System.Single[], mscorlib",
            "$values": [
              10.0,
              0.0,
              0.0,
              0.0,
              0.0
            ]
          }
        },
        "ItemPercentiles": {
          "$type": "Game.GameMode.StorySession.GameBoard.Simulation.Utilities.StatSet, Game.GameMode.StorySession",
          "Stats": {
            "$type": "System.Single[], mscorlib",
            "$values": [
              1.0,
              1.0,
              1.0,
              1.0,
              1.0
            ]
          }
        }
      },
      "MaxCharge": {
        "$type": "Game.GameMode.StorySession.GameBoard.Simulation.Items.Enteties.Special.ItemStatSets.ItemStatEntry, Game.GameMode.StorySession",
        "ItemValues": {
          "$type": "Game.GameMode.StorySession.GameBoard.Simulation.Utilities.StatSet, Game.GameMode.StorySession",
          "Stats": {
            "$type": "System.Single[], mscorlib",
            "$values": [
              7.0,
              0.0,
              0.0,
              0.0,
              0.0
            ]
          }
        },
        "ItemPercentiles": {
          "$type": "Game.GameMode.StorySession.GameBoard.Simulation.Utilities.StatSet, Game.GameMode.StorySession",
          "Stats": {
            "$type": "System.Single[], mscorlib",
            "$values": [
              1.0,
              1.0,
              1.0,
              1.0,
              1.0
            ]
          }
        }
      },
      "ChargeSpeed": {
        "$type": "Game.GameMode.StorySession.GameBoard.Simulation.Items.Enteties.Special.ItemStatSets.ItemStatEntry, Game.GameMode.StorySession",
        "ItemValues": {
          "$type": "Game.GameMode.StorySession.GameBoard.Simulation.Utilities.StatSet, Game.GameMode.StorySession",
          "Stats": {
            "$type": "System.Single[], mscorlib",
            "$values": [
              1.0,
              0.0,
              0.0,
              0.0,
              0.0
            ]
          }
        },
        "ItemPercentiles": {
          "$type": "Game.GameMode.StorySession.GameBoard.Simulation.Utilities.StatSet, Game.GameMode.StorySession",
          "Stats": {
            "$type": "System.Single[], mscorlib",
            "$values": [
              1.0,
              1.0,
              1.0,
              1.0,
              1.0
            ]
          }
        }
      },
      "UsageCount": {
        "$type": "Game.GameMode.StorySession.GameBoard.Simulation.Items.Enteties.Special.ItemStatSets.ItemStatEntry, Game.GameMode.StorySession",
        "ItemValues": {
          "$type": "Game.GameMode.StorySession.GameBoard.Simulation.Utilities.StatSet, Game.GameMode.StorySession",
          "Stats": {
            "$type": "System.Single[], mscorlib",
            "$values": [
              1.0,
              0.0,
              0.0,
              0.0,
              0.0
            ]
          }
        },
        "ItemPercentiles": {
          "$type": "Game.GameMode.StorySession.GameBoard.Simulation.Utilities.StatSet, Game.GameMode.StorySession",
          "Stats": {
            "$type": "System.Single[], mscorlib",
            "$values": [
              1.0,
              1.0,
              1.0,
              1.0,
              1.0
            ]
          }
        }
      }
    },
    "IsCooldownItem": true,
    "CurrentCharge": 0.0
  }
}